<?xml version="1.0" encoding="UTF-8"?>
<metadata xml:lang="sl"><Esri><CreaDate>20201201</CreaDate><CreaTime>11314600</CreaTime><ArcGISFormat>1.0</ArcGISFormat><SyncOnce>TRUE</SyncOnce><DataProperties><lineage><Process ToolSource="c:\program files (x86)\arcgis\desktop10.6\ArcToolbox\Toolboxes\Data Management Tools.tbx\Project" Date="20201201" Time="113146">Project 110020140909_ILL C:\_DOCS\FGG\2020-2021\ERAS_SPFP_mundus\tutorial\tut1\roads\Roads_SLO_d96.shp PROJCS['Slovenia_1996_Slovene_National_Grid',GEOGCS['GCS_Slovenia_1996',DATUM['D_Slovenia_Geodetic_Datum_1996',SPHEROID['GRS_1980',6378137.0,298.257222101]],PRIMEM['Greenwich',0.0],UNIT['Degree',0.0174532925199433]],PROJECTION['Transverse_Mercator'],PARAMETER['False_Easting',500000.0],PARAMETER['False_Northing',-5000000.0],PARAMETER['Central_Meridian',15.0],PARAMETER['Scale_Factor',0.9999],PARAMETER['Latitude_Of_Origin',0.0],UNIT['Meter',1.0]] MGI_1901_To_Slovenia_1996_1 PROJCS['MGI 1901 / Slovene National Grid',GEOGCS['MGI 1901',DATUM['MGI 1901',SPHEROID['Bessel 1841',6377397.155,299.1528128]],PRIMEM['Greenwich',0.0],UNIT['degree',0.0174532925199433]],PROJECTION['Transverse_Mercator'],PARAMETER['false_easting',500000.0],PARAMETER['false_northing',-5000000.0],PARAMETER['central_meridian',15.0],PARAMETER['scale_factor',0.9999],PARAMETER['latitude_of_origin',0.0],UNIT['m',1.0]] NO_PRESERVE_SHAPE # NO_VERTICAL</Process></lineage></DataProperties></Esri></metadata>
